trident/__init__.py
trident/client.py
izihawa_trident-1.0.48.dist-info/METADATA
izihawa_trident-1.0.48.dist-info/WHEEL
izihawa_trident-1.0.48.dist-info/RECORD
